{"cameraMode":{"drawMode":0,"name":"Shaded","section":"Shading Mode"},"sceneLighting":false,"audioPlay":false,"sceneViewState":{"m_AlwaysRefresh":false,"showFog":true,"showSkybox":true,"showFlares":true,"showImageEffects":true,"showParticleSystems":true,"showVisualEffectGraphs":true,"m_FxEnabled":true},"in2DMode":false,"pivot":{"x":-354.4870910644531,"y":-216.15065002441407,"z":585.6118774414063},"rotation":{"x":-0.28289443254470827,"y":0.31107333302497866,"z":-0.0970793142914772,"w":-0.9025898575782776},"size":274.0191650390625,"orthographic":false}